qtip_cli/__init__.py
qtip_cli/qtip.py
qtip_cli/actions/__init__.py
qtip_cli/actions/upload_and_serve_file.py
qtip_cli/actions/preview/__init__.py
qtip_cli/actions/preview/preview.py
qtip_cli/helpers/__init__.py
qtip_cli/helpers/args.py
qtip_cli/helpers/env.py
qtip_client_cli-0.1.2.dist-info/METADATA
qtip_client_cli-0.1.2.dist-info/WHEEL
qtip_client_cli-0.1.2.dist-info/entry_points.txt
qtip_client_cli-0.1.2.dist-info/top_level.txt
qtip_client_cli-0.1.2.dist-info/RECORD
